matplotlib_dashboard/__init__.py
matplotlib_dashboard/matplotlib_dashboard.py
matplotlib_dashboard-0.0.4.dist-info/LICENSE
matplotlib_dashboard-0.0.4.dist-info/METADATA
matplotlib_dashboard-0.0.4.dist-info/WHEEL
matplotlib_dashboard-0.0.4.dist-info/top_level.txt
matplotlib_dashboard-0.0.4.dist-info/RECORD
