Metadata-Version: 2.1
Name: matplotlib-dashboard
Version: 0.0.4
Summary: This package, with the aim of accelerating and facilitating the use of some design patterns, offers abstract classes.
Home-page: https://github.com/BehzadShayegh/matplotlib-dashboard
Author: Behzad Shayegh
Author-email: behzad.shayegh@ut.ac.ir
License: UNKNOWN
Project-URL: Bug Tracker, https://github.com/BehzadShayegh/matplotlib-dashboard/issues
Platform: UNKNOWN
Classifier: Programming Language :: Python :: 3
Classifier: License :: OSI Approved :: MIT License
Classifier: Operating System :: OS Independent
Requires-Python: >=3.6
License-File: LICENSE
